data_email_client/__init__.py
data_email_client/data_email_gui.py
data_email_client/email_client.py
data_email_client/common/__init__.py
data_email_client/common/log.py
data_email_client/common/models.py
data_email_client/common/utils.py
data_email_client-0.4.0.dist-info/METADATA
data_email_client-0.4.0.dist-info/WHEEL
data_email_client-0.4.0.dist-info/top_level.txt
data_email_client-0.4.0.dist-info/RECORD
