Metadata-Version: 2.2
Name: data_email_client
Version: 0.4.0
Summary: A simple python email client for downloading email attachments
Author-email: David Carlson <drc@nrgsystems.com>
Project-URL: Repository, https://github.com/nrgpy/data_email_client
Keywords: email,attachments,client,download,nrg systems,data
Classifier: License :: OSI Approved :: MIT License
Classifier: Natural Language :: English
Classifier: Operating System :: OS Independent
Classifier: Programming Language :: Python :: 3
Requires-Python: >=3.6
Requires-Dist: cryptography
Requires-Dist: pydantic
Provides-Extra: dev
Requires-Dist: black; extra == "dev"
Requires-Dist: rich; extra == "dev"
Requires-Dist: jupyterlab; extra == "dev"
Requires-Dist: pyinstaller; extra == "dev"
